springlabs_django/__init__.py
springlabs_django/main.py
springlabs_django/primary_functions.py
springlabs_django/utils.py
springlabs_django/validators.py
springlabs_django/core/__init__.py
springlabs_django/core/new_api/__init__.py
springlabs_django/core/new_api/api/__init__.py
springlabs_django/core/new_api/api/delete_serializers_model.py
springlabs_django/core/new_api/api/delete_serializers_open.py
springlabs_django/core/new_api/api/delete_views_model.py
springlabs_django/core/new_api/api/delete_views_open.py
springlabs_django/core/new_api/api/post_serializers_model.py
springlabs_django/core/new_api/api/post_serializers_open.py
springlabs_django/core/new_api/api/post_views_model.py
springlabs_django/core/new_api/api/post_views_open.py
springlabs_django/core/new_api/api/put_serializers_model.py
springlabs_django/core/new_api/api/put_serializers_open.py
springlabs_django/core/new_api/api/put_views_model.py
springlabs_django/core/new_api/api/put_views_open.py
springlabs_django/core/new_graph/__init__.py
springlabs_django/core/new_graph/graph/__init__.py
springlabs_django/core/new_graph/graph/schema.py
springlabs_django/core/new_graph/graph/types_model.py
springlabs_django/core/new_graph/graph/types_open.py
springlabs_django/core/new_group/__init__.py
springlabs_django/core/new_group/graph/__init__.py
springlabs_django/core/new_group/graph/initial_schema.py
springlabs_django/core/new_group/graph/initial_type.py
springlabs_django/core/new_version/__init__.py
springlabs_django/core/new_version/api/__init__.py
springlabs_django/core/new_version/api/baseApi.py
springlabs_django/core/new_version/api/basePrivateUrls.py
springlabs_django/core/new_version/api/basePublicUrls.py
springlabs_django/core/new_version/api/baseSerializers.py
springlabs_django/core/new_version/api/baseUrls.py
springlabs_django/core/new_version/api/baseViews.py
springlabs_django/core/new_version/graphql_api/__init__.py
springlabs_django/core/new_version/graphql_api/baseApi.py
springlabs_django-0.3.5.dist-info/LICENSE
springlabs_django-0.3.5.dist-info/METADATA
springlabs_django-0.3.5.dist-info/WHEEL
springlabs_django-0.3.5.dist-info/entry_points.txt
springlabs_django-0.3.5.dist-info/top_level.txt
springlabs_django-0.3.5.dist-info/RECORD
